{
  "_meta": {
    "id": "di_tax_extraction_tax_individual_income_return",
    "version": "2.0.0",
    "description": "Extraction hints for tax_individual_income_return.",
    "languages": [
      "any"
    ],
    "lastUpdated": "2026-02-28",
    "owner": "data-bank-governance",
    "usedBy": [
      "services/core/banks/dataBankLoader.service.ts"
    ],
    "tests": [
      "tests/patternWiringProof.test.ts"
    ]
  },
  "config": {
    "enabled": true,
    "domain": "tax",
    "docType": "tax_individual_income_return"
  },
  "hints": [
    {
      "id": "hint_01_document_id",
      "entity": "document_id",
      "anchors": [
        "document id",
        "tax_individual_income_return",
        "document number",
        "numero do documento",
        "reference",
        "protocolo",
        "annex",
        "anexo",
        "exhibit",
        "apenso",
        "footnote",
        "nota de rodape",
        "document_id",
        "document_id value",
        "document_id campo"
      ],
      "location": "document_identification",
      "extractionMethod": "heading_proximity"
    },
    {
      "id": "hint_02_issuer_name",
      "entity": "issuer_name",
      "anchors": [
        "issuer name",
        "tax_individual_income_return",
        "document number",
        "numero do documento",
        "reference",
        "protocolo",
        "annex",
        "anexo",
        "exhibit",
        "apenso",
        "footnote",
        "nota de rodape",
        "issuer_name",
        "issuer_name value",
        "issuer_name campo"
      ],
      "location": "issuer_information",
      "extractionMethod": "table_header_row_context"
    },
    {
      "id": "hint_03_subject_name",
      "entity": "subject_name",
      "anchors": [
        "subject name",
        "tax_individual_income_return",
        "document number",
        "numero do documento",
        "reference",
        "protocolo",
        "annex",
        "anexo",
        "exhibit",
        "apenso",
        "footnote",
        "nota de rodape",
        "subject_name",
        "subject_name value",
        "subject_name campo"
      ],
      "location": "party_identification",
      "extractionMethod": "key_value_pattern"
    },
    {
      "id": "hint_04_document_number",
      "entity": "document_number",
      "anchors": [
        "document number",
        "tax_individual_income_return",
        "numero do documento",
        "reference",
        "protocolo",
        "annex",
        "anexo",
        "exhibit",
        "apenso",
        "footnote",
        "nota de rodape",
        "document_number",
        "document_number value",
        "document_number campo"
      ],
      "location": "period_and_jurisdiction",
      "extractionMethod": "regex_plus_context"
    },
    {
      "id": "hint_05_issue_date",
      "entity": "issue_date",
      "anchors": [
        "issue date",
        "tax_individual_income_return",
        "document number",
        "numero do documento",
        "reference",
        "protocolo",
        "annex",
        "anexo",
        "exhibit",
        "apenso",
        "footnote",
        "nota de rodape",
        "issue_date",
        "issue_date value",
        "issue_date campo"
      ],
      "location": "status_and_summary",
      "extractionMethod": "heading_proximity"
    },
    {
      "id": "hint_06_effective_date",
      "entity": "effective_date",
      "anchors": [
        "effective date",
        "tax_individual_income_return",
        "document number",
        "numero do documento",
        "reference",
        "protocolo",
        "annex",
        "anexo",
        "exhibit",
        "apenso",
        "footnote",
        "nota de rodape",
        "effective_date",
        "effective_date value",
        "effective_date campo"
      ],
      "location": "line_items",
      "extractionMethod": "table_header_row_context"
    },
    {
      "id": "hint_07_period_start",
      "entity": "period_start",
      "anchors": [
        "period start",
        "tax_individual_income_return",
        "document number",
        "numero do documento",
        "reference",
        "protocolo",
        "annex",
        "anexo",
        "exhibit",
        "apenso",
        "footnote",
        "nota de rodape",
        "period_start",
        "period_start value",
        "period_start campo"
      ],
      "location": "calculation_basis",
      "extractionMethod": "key_value_pattern"
    },
    {
      "id": "hint_08_period_end",
      "entity": "period_end",
      "anchors": [
        "period end",
        "tax_individual_income_return",
        "document number",
        "numero do documento",
        "reference",
        "protocolo",
        "annex",
        "anexo",
        "exhibit",
        "apenso",
        "footnote",
        "nota de rodape",
        "period_end",
        "period_end value",
        "period_end campo"
      ],
      "location": "critical_dates",
      "extractionMethod": "regex_plus_context"
    },
    {
      "id": "hint_09_jurisdiction",
      "entity": "jurisdiction",
      "anchors": [
        "jurisdiction",
        "tax_individual_income_return",
        "document number",
        "numero do documento",
        "reference",
        "protocolo",
        "annex",
        "anexo",
        "exhibit",
        "apenso",
        "footnote",
        "nota de rodape",
        "jurisdiction value",
        "jurisdiction campo"
      ],
      "location": "obligations_and_conditions",
      "extractionMethod": "heading_proximity"
    },
    {
      "id": "hint_10_status",
      "entity": "status",
      "anchors": [
        "status",
        "tax_individual_income_return",
        "document number",
        "numero do documento",
        "reference",
        "protocolo",
        "annex",
        "anexo",
        "exhibit",
        "apenso",
        "footnote",
        "nota de rodape",
        "status value",
        "status campo"
      ],
      "location": "supporting_documents",
      "extractionMethod": "table_header_row_context"
    },
    {
      "id": "hint_11_currency",
      "entity": "currency",
      "anchors": [
        "currency",
        "tax_individual_income_return",
        "document number",
        "numero do documento",
        "reference",
        "protocolo",
        "annex",
        "anexo",
        "exhibit",
        "apenso",
        "footnote",
        "nota de rodape",
        "currency value",
        "currency campo"
      ],
      "location": "annexes_exhibits",
      "extractionMethod": "key_value_pattern"
    },
    {
      "id": "hint_12_total_amount",
      "entity": "total_amount",
      "anchors": [
        "total amount",
        "tax_individual_income_return",
        "document number",
        "numero do documento",
        "reference",
        "protocolo",
        "annex",
        "anexo",
        "exhibit",
        "apenso",
        "footnote",
        "nota de rodape",
        "total_amount",
        "total_amount value",
        "total_amount campo"
      ],
      "location": "footnotes",
      "extractionMethod": "regex_plus_context"
    },
    {
      "id": "hint_13_due_date",
      "entity": "due_date",
      "anchors": [
        "due date",
        "tax_individual_income_return",
        "document number",
        "numero do documento",
        "reference",
        "protocolo",
        "annex",
        "anexo",
        "exhibit",
        "apenso",
        "footnote",
        "nota de rodape",
        "due_date",
        "due_date value",
        "due_date campo"
      ],
      "location": "signatures_attestations",
      "extractionMethod": "heading_proximity"
    },
    {
      "id": "hint_14_reference_id",
      "entity": "reference_id",
      "anchors": [
        "reference id",
        "tax_individual_income_return",
        "document number",
        "numero do documento",
        "reference",
        "protocolo",
        "annex",
        "anexo",
        "exhibit",
        "apenso",
        "footnote",
        "nota de rodape",
        "reference_id",
        "reference_id value",
        "reference_id campo"
      ],
      "location": "contacts_and_instructions",
      "extractionMethod": "table_header_row_context"
    },
    {
      "id": "hint_15_source_table_ref",
      "entity": "source_table_ref",
      "anchors": [
        "source table ref",
        "tax_individual_income_return",
        "document number",
        "numero do documento",
        "reference",
        "protocolo",
        "annex",
        "anexo",
        "exhibit",
        "apenso",
        "footnote",
        "nota de rodape",
        "source_table_ref",
        "source_table_ref value",
        "source_table_ref campo"
      ],
      "location": "annex_a",
      "extractionMethod": "key_value_pattern"
    },
    {
      "id": "hint_16_taxpayer_id",
      "entity": "taxpayer_id",
      "anchors": [
        "taxpayer id",
        "tax_individual_income_return",
        "document number",
        "numero do documento",
        "reference",
        "protocolo",
        "annex",
        "anexo",
        "exhibit",
        "apenso",
        "footnote",
        "nota de rodape",
        "taxpayer_id",
        "taxpayer_id value",
        "taxpayer_id campo"
      ],
      "location": "annex_b",
      "extractionMethod": "regex_plus_context"
    },
    {
      "id": "hint_17_filing_status",
      "entity": "filing_status",
      "anchors": [
        "filing status",
        "tax_individual_income_return",
        "document number",
        "numero do documento",
        "reference",
        "protocolo",
        "annex",
        "anexo",
        "exhibit",
        "apenso",
        "footnote",
        "nota de rodape",
        "filing_status",
        "filing_status value",
        "filing_status campo"
      ],
      "location": "appendix",
      "extractionMethod": "heading_proximity"
    },
    {
      "id": "hint_18_tax_year",
      "entity": "tax_year",
      "anchors": [
        "tax year",
        "tax_individual_income_return",
        "document number",
        "numero do documento",
        "reference",
        "protocolo",
        "annex",
        "anexo",
        "exhibit",
        "apenso",
        "footnote",
        "nota de rodape",
        "tax_year",
        "tax_year value",
        "tax_year campo"
      ],
      "location": "exhibit_index",
      "extractionMethod": "table_header_row_context"
    },
    {
      "id": "hint_19_gross_income",
      "entity": "gross_income",
      "anchors": [
        "gross income",
        "tax_individual_income_return",
        "document number",
        "numero do documento",
        "reference",
        "protocolo",
        "annex",
        "anexo",
        "exhibit",
        "apenso",
        "footnote",
        "nota de rodape",
        "gross_income",
        "gross_income value",
        "gross_income campo"
      ],
      "location": "schedule_1",
      "extractionMethod": "key_value_pattern"
    },
    {
      "id": "hint_20_taxable_income",
      "entity": "taxable_income",
      "anchors": [
        "taxable income",
        "tax_individual_income_return",
        "document number",
        "numero do documento",
        "reference",
        "protocolo",
        "annex",
        "anexo",
        "exhibit",
        "apenso",
        "footnote",
        "nota de rodape",
        "taxable_income",
        "taxable_income value",
        "taxable_income campo"
      ],
      "location": "schedule_2",
      "extractionMethod": "regex_plus_context"
    },
    {
      "id": "hint_21_total_deductions",
      "entity": "total_deductions",
      "anchors": [
        "total deductions",
        "tax_individual_income_return",
        "document number",
        "numero do documento",
        "reference",
        "protocolo",
        "annex",
        "anexo",
        "exhibit",
        "apenso",
        "footnote",
        "nota de rodape",
        "total_deductions",
        "total_deductions value",
        "total_deductions campo"
      ],
      "location": "footer",
      "extractionMethod": "heading_proximity"
    },
    {
      "id": "hint_22_total_credits",
      "entity": "total_credits",
      "anchors": [
        "total credits",
        "tax_individual_income_return",
        "document number",
        "numero do documento",
        "reference",
        "protocolo",
        "annex",
        "anexo",
        "exhibit",
        "apenso",
        "footnote",
        "nota de rodape",
        "total_credits",
        "total_credits value",
        "total_credits campo"
      ],
      "location": "header",
      "extractionMethod": "table_header_row_context"
    },
    {
      "id": "hint_23_tax_liability",
      "entity": "tax_liability",
      "anchors": [
        "tax liability",
        "tax_individual_income_return",
        "document number",
        "numero do documento",
        "reference",
        "protocolo",
        "annex",
        "anexo",
        "exhibit",
        "apenso",
        "footnote",
        "nota de rodape",
        "tax_liability",
        "tax_liability value",
        "tax_liability campo"
      ],
      "location": "table_notes",
      "extractionMethod": "key_value_pattern"
    },
    {
      "id": "hint_24_refund_amount",
      "entity": "refund_amount",
      "anchors": [
        "refund amount",
        "tax_individual_income_return",
        "document number",
        "numero do documento",
        "reference",
        "protocolo",
        "annex",
        "anexo",
        "exhibit",
        "apenso",
        "footnote",
        "nota de rodape",
        "refund_amount",
        "refund_amount value",
        "refund_amount campo"
      ],
      "location": "back_page",
      "extractionMethod": "regex_plus_context"
    },
    {
      "id": "hint_25_amount_due",
      "entity": "amount_due",
      "anchors": [
        "amount due",
        "tax_individual_income_return",
        "document number",
        "numero do documento",
        "reference",
        "protocolo",
        "annex",
        "anexo",
        "exhibit",
        "apenso",
        "footnote",
        "nota de rodape",
        "amount_due",
        "amount_due value",
        "amount_due campo"
      ],
      "location": "document_identification",
      "extractionMethod": "heading_proximity"
    },
    {
      "id": "hint_26_submission_reference",
      "entity": "submission_reference",
      "anchors": [
        "submission reference",
        "tax_individual_income_return",
        "document number",
        "numero do documento",
        "reference",
        "protocolo",
        "annex",
        "anexo",
        "exhibit",
        "apenso",
        "footnote",
        "nota de rodape",
        "submission_reference",
        "submission_reference value",
        "submission_reference campo"
      ],
      "location": "issuer_information",
      "extractionMethod": "table_header_row_context"
    },
    {
      "id": "hint_27_tax_doc_type",
      "entity": "tax_doc_type",
      "anchors": [
        "tax doc type",
        "tax_individual_income_return",
        "document number",
        "numero do documento",
        "reference",
        "protocolo",
        "annex",
        "anexo",
        "exhibit",
        "apenso",
        "footnote",
        "nota de rodape",
        "tax_doc_type",
        "tax_doc_type value",
        "tax_doc_type campo"
      ],
      "location": "party_identification",
      "extractionMethod": "key_value_pattern"
    }
  ]
}
