{
  "_meta": {
    "id": "allybi_xlsx_operators",
    "version": "1.0.0",
    "description": "Deterministic XLSX operator catalog with strict schemas and runtime mapping.",
    "languages": [
      "any",
      "en",
      "pt"
    ],
    "lastUpdated": "2026-02-27",
    "owner": "allybi-editing",
    "usedBy": [
      "services/core/banks/dataBankLoader.service.ts"
    ],
    "tests": [
      "tests/patternWiringProof.test.ts"
    ]
  },
  "config": {
    "enabled": true,
    "filetype": "xlsx",
    "pythonFallback": {
      "enabled": true,
      "operatorBankId": "allybi_python_operators",
      "escalateWhen": [
        "computation_exceeds_single_formula",
        "multi_sheet_join_required",
        "statistical_analysis_requested",
        "chart_as_image_requested",
        "data_cleaning_requires_fuzzy_match",
        "time_series_forecast_requested",
        "pivot_with_custom_aggregation"
      ]
    }
  },
  "operators": {
    "XLSX_SET_CELL_VALUE": {
      "runtimeOperator": "EDIT_CELL",
      "preview_render_type": "cell_diff",
      "requires_confirmation": false,
      "undo_strategy": "restore_previous_cell",
      "schema": {
        "type": "object",
        "required": [
          "targetId",
          "value"
        ],
        "properties": {
          "targetId": {
            "type": "string"
          },
          "value": {}
        }
      },
      "examples_en": [
        "Apply set cell value to the selected range.",
        "Run set cell value on SUMMARY 1!D35:D48.",
        "Please set cell value in the current sheet selection.",
        "Do set cell value only on the highlighted cells.",
        "Set up set cell value without changing unrelated cells."
      ],
      "examples_pt": [
        "Aplique set cell value no intervalo selecionado.",
        "Execute set cell value em SUMMARY 1!D35:D48.",
        "Por favor, faça set cell value na seleção da planilha atual.",
        "Faça set cell value apenas nas células destacadas.",
        "Configure set cell value sem alterar células não relacionadas."
      ]
    },
    "XLSX_SET_RANGE_VALUES": {
      "runtimeOperator": "EDIT_RANGE",
      "preview_render_type": "cell_diff",
      "requires_confirmation": true,
      "undo_strategy": "restore_previous_range",
      "schema": {
        "type": "object",
        "required": [
          "rangeA1",
          "values"
        ],
        "properties": {
          "rangeA1": {
            "type": "string"
          },
          "values": {
            "type": "array"
          }
        }
      },
      "examples_en": [
        "Apply set range values to the selected range.",
        "Run set range values on SUMMARY 1!D35:D48.",
        "Please set range values in the current sheet selection.",
        "Do set range values only on the highlighted cells.",
        "Set up set range values without changing unrelated cells."
      ],
      "examples_pt": [
        "Aplique set range values no intervalo selecionado.",
        "Execute set range values em SUMMARY 1!D35:D48.",
        "Por favor, faça set range values na seleção da planilha atual.",
        "Faça set range values apenas nas células destacadas.",
        "Configure set range values sem alterar células não relacionadas."
      ]
    },
    "XLSX_SET_CELL_FORMULA": {
      "runtimeOperator": "COMPUTE_BUNDLE",
      "preview_render_type": "cell_diff",
      "requires_confirmation": false,
      "undo_strategy": "restore_previous_cell",
      "schema": {
        "type": "object",
        "required": [
          "rangeA1",
          "formula"
        ],
        "properties": {
          "rangeA1": {
            "type": "string"
          },
          "formula": {
            "type": "string"
          }
        }
      },
      "examples_en": [
        "Apply set cell formula to the selected range.",
        "Run set cell formula on SUMMARY 1!D35:D48.",
        "Please set cell formula in the current sheet selection.",
        "Do set cell formula only on the highlighted cells.",
        "Set up set cell formula without changing unrelated cells."
      ],
      "examples_pt": [
        "Aplique set cell formula no intervalo selecionado.",
        "Execute set cell formula em SUMMARY 1!D35:D48.",
        "Por favor, faça set cell formula na seleção da planilha atual.",
        "Faça set cell formula apenas nas células destacadas.",
        "Configure set cell formula sem alterar células não relacionadas."
      ]
    },
    "XLSX_SET_RANGE_FORMULAS": {
      "runtimeOperator": "COMPUTE_BUNDLE",
      "preview_render_type": "cell_diff",
      "requires_confirmation": true,
      "undo_strategy": "restore_previous_range",
      "schema": {
        "type": "object",
        "required": [
          "rangeA1",
          "formula"
        ],
        "properties": {
          "rangeA1": {
            "type": "string"
          },
          "formula": {
            "type": "string"
          }
        }
      },
      "examples_en": [
        "Apply set range formulas to the selected range.",
        "Run set range formulas on SUMMARY 1!D35:D48.",
        "Please set range formulas in the current sheet selection.",
        "Do set range formulas only on the highlighted cells.",
        "Set up set range formulas without changing unrelated cells."
      ],
      "examples_pt": [
        "Aplique set range formulas no intervalo selecionado.",
        "Execute set range formulas em SUMMARY 1!D35:D48.",
        "Por favor, faça set range formulas na seleção da planilha atual.",
        "Faça set range formulas apenas nas células destacadas.",
        "Configure set range formulas sem alterar células não relacionadas."
      ]
    },
    "XLSX_FILL_DOWN": {
      "runtimeOperator": "EDIT_RANGE",
      "preview_render_type": "cell_diff",
      "requires_confirmation": false,
      "undo_strategy": "snapshot",
      "schema": {
        "type": "object",
        "required": [
          "rangeA1"
        ],
        "properties": {
          "rangeA1": {
            "type": "string",
            "description": "Target range in A1 notation, e.g. B2:B100"
          },
          "sourceRow": {
            "type": "number",
            "description": "1-based row number of the source cell to copy from"
          },
          "value": {
            "description": "Static value to fill down"
          },
          "formula": {
            "type": "string",
            "description": "Formula to fill down with relative references adjusted"
          }
        }
      },
      "examples_en": [
        "Fill down the formula from B2 to B2:B100",
        "Copy the value from A1 down to A1:A20"
      ],
      "examples_pt": [
        "Preencher para baixo a fórmula de B2 até B2:B100",
        "Copiar o valor de A1 para baixo até A1:A20"
      ]
    },
    "XLSX_FILL_RIGHT": {
      "runtimeOperator": "EDIT_RANGE",
      "preview_render_type": "cell_diff",
      "requires_confirmation": false,
      "undo_strategy": "snapshot",
      "schema": {
        "type": "object",
        "required": [
          "rangeA1"
        ],
        "properties": {
          "rangeA1": {
            "type": "string",
            "description": "Target range in A1 notation, e.g. A1:E1"
          },
          "sourceCol": {
            "type": "number",
            "description": "1-based column number of the source cell to copy from"
          },
          "value": {
            "description": "Static value to fill right"
          },
          "formula": {
            "type": "string",
            "description": "Formula to fill right with relative references adjusted"
          }
        }
      },
      "examples_en": [
        "Fill right from A1 to A1:E1",
        "Copy formula from A2 across to E2"
      ],
      "examples_pt": [
        "Preencher para direita de A1 até E1",
        "Copiar fórmula de A2 até E2"
      ]
    },
    "XLSX_FILL_SERIES": {
      "runtimeOperator": "EDIT_RANGE",
      "preview_render_type": "cell_diff",
      "requires_confirmation": false,
      "undo_strategy": "snapshot",
      "schema": {
        "type": "object",
        "required": [
          "rangeA1"
        ],
        "properties": {
          "rangeA1": {
            "type": "string",
            "description": "Target range in A1 notation, e.g. A1:A20"
          },
          "startValue": {
            "type": "number",
            "description": "Starting value for the series"
          },
          "step": {
            "type": "number",
            "description": "Increment between consecutive values"
          },
          "type": {
            "type": "string",
            "enum": [
              "linear",
              "date"
            ],
            "description": "Series type: linear for numeric sequences, date for date sequences"
          }
        }
      },
      "examples_en": [
        "Fill A1:A20 with numbers 1 to 20",
        "Create a date series from Jan 1 to Jan 31"
      ],
      "examples_pt": [
        "Preencher A1:A20 com números de 1 a 20",
        "Criar série de datas de 1 a 31 de janeiro"
      ]
    },
    "XLSX_FORMAT_RANGE": {
      "runtimeOperator": "COMPUTE_BUNDLE",
      "preview_render_type": "format_diff",
      "requires_confirmation": true,
      "undo_strategy": "restore_previous_format",
      "schema": {
        "type": "object",
        "required": [
          "rangeA1"
        ],
        "properties": {
          "rangeA1": {
            "type": "string"
          },
          "format": {
            "type": "object"
          }
        }
      },
      "examples_en": [
        "Apply format range to the selected range.",
        "Run format range on SUMMARY 1!D35:D48.",
        "Please format range in the current sheet selection.",
        "Do format range only on the highlighted cells.",
        "Set up format range without changing unrelated cells."
      ],
      "examples_pt": [
        "Aplique format range no intervalo selecionado.",
        "Execute format range em SUMMARY 1!D35:D48.",
        "Por favor, faça format range na seleção da planilha atual.",
        "Faça format range apenas nas células destacadas.",
        "Configure format range sem alterar células não relacionadas."
      ]
    },
    "XLSX_SET_NUMBER_FORMAT": {
      "runtimeOperator": "COMPUTE_BUNDLE",
      "preview_render_type": "format_diff",
      "requires_confirmation": true,
      "undo_strategy": "restore_previous_format",
      "schema": {
        "type": "object",
        "required": [
          "rangeA1",
          "pattern"
        ],
        "properties": {
          "rangeA1": {
            "type": "string"
          },
          "pattern": {
            "type": "string"
          }
        }
      },
      "examples_en": [
        "Apply set number format to the selected range.",
        "Run set number format on SUMMARY 1!D35:D48.",
        "Please set number format in the current sheet selection.",
        "Do set number format only on the highlighted cells.",
        "Set up set number format without changing unrelated cells."
      ],
      "examples_pt": [
        "Aplique set number format no intervalo selecionado.",
        "Execute set number format em SUMMARY 1!D35:D48.",
        "Por favor, faça set number format na seleção da planilha atual.",
        "Faça set number format apenas nas células destacadas.",
        "Configure set number format sem alterar células não relacionadas."
      ]
    },
    "XLSX_MERGE_CELLS": {
      "runtimeOperator": "EDIT_RANGE",
      "preview_render_type": "structural_diff",
      "requires_confirmation": true,
      "undo_strategy": "snapshot",
      "schema": {
        "type": "object",
        "required": [
          "rangeA1"
        ],
        "properties": {
          "rangeA1": {
            "type": "string",
            "description": "Range to merge in A1 notation, e.g. A1:C1"
          }
        }
      },
      "examples_en": [
        "Merge cells A1 to C1",
        "Combine A1:D1 into one cell"
      ],
      "examples_pt": [
        "Mesclar células A1 até C1",
        "Combinar A1:D1 em uma célula"
      ]
    },
    "XLSX_WRAP_TEXT": {
      "runtimeOperator": "EDIT_RANGE",
      "preview_render_type": "format_diff",
      "requires_confirmation": false,
      "undo_strategy": "snapshot",
      "schema": {
        "type": "object",
        "required": [
          "rangeA1"
        ],
        "properties": {
          "rangeA1": {
            "type": "string",
            "description": "Range to apply text wrapping to, in A1 notation"
          }
        }
      },
      "examples_en": [
        "Wrap text in column A",
        "Enable text wrapping for A1:D10"
      ],
      "examples_pt": [
        "Quebrar texto na coluna A",
        "Ativar quebra de texto em A1:D10"
      ]
    },
    "XLSX_AUTO_FIT": {
      "runtimeOperator": "EDIT_RANGE",
      "preview_render_type": "format_diff",
      "requires_confirmation": false,
      "undo_strategy": "snapshot",
      "schema": {
        "type": "object",
        "properties": {
          "columns": {
            "type": "array",
            "items": {
              "type": "number"
            },
            "description": "1-based column numbers to auto-fit"
          },
          "rangeA1": {
            "type": "string",
            "description": "Range whose columns should be auto-fitted, in A1 notation"
          }
        }
      },
      "examples_en": [
        "Auto-fit column widths for columns A to D",
        "Resize columns to fit content"
      ],
      "examples_pt": [
        "Ajustar largura das colunas A até D",
        "Redimensionar colunas para caber conteúdo"
      ]
    },
    "XLSX_COND_FORMAT_DATA_BARS": {
      "runtimeOperator": "EDIT_RANGE",
      "preview_render_type": "format_diff",
      "requires_confirmation": false,
      "undo_strategy": "snapshot",
      "schema": {
        "type": "object",
        "required": [
          "rangeA1"
        ],
        "properties": {
          "rangeA1": {
            "type": "string",
            "description": "Range to apply data bars to, in A1 notation"
          },
          "color": {
            "type": "string",
            "description": "Hex color for the data bars, e.g. #4472C4"
          }
        }
      },
      "examples_en": [
        "Add data bars to B2:B20",
        "Show data bars in blue for the revenue column"
      ],
      "examples_pt": [
        "Adicionar barras de dados em B2:B20",
        "Mostrar barras de dados em azul na coluna de receita"
      ]
    },
    "XLSX_COND_FORMAT_COLOR_SCALE": {
      "runtimeOperator": "EDIT_RANGE",
      "preview_render_type": "format_diff",
      "requires_confirmation": false,
      "undo_strategy": "snapshot",
      "schema": {
        "type": "object",
        "required": [
          "rangeA1"
        ],
        "properties": {
          "rangeA1": {
            "type": "string",
            "description": "Range to apply color scale to, in A1 notation"
          },
          "minColor": {
            "type": "string",
            "description": "Hex color for the minimum value, e.g. #FF0000"
          },
          "maxColor": {
            "type": "string",
            "description": "Hex color for the maximum value, e.g. #00B050"
          },
          "midColor": {
            "type": "string",
            "description": "Hex color for the midpoint value (optional 3-color scale)"
          }
        }
      },
      "examples_en": [
        "Apply color scale from red to green on B2:B20",
        "Add heat map colors to the margin column"
      ],
      "examples_pt": [
        "Aplicar escala de cores de vermelho a verde em B2:B20",
        "Adicionar cores de mapa de calor na coluna de margem"
      ]
    },
    "XLSX_COND_FORMAT_TOP_N": {
      "runtimeOperator": "EDIT_RANGE",
      "preview_render_type": "format_diff",
      "requires_confirmation": false,
      "undo_strategy": "snapshot",
      "schema": {
        "type": "object",
        "required": [
          "rangeA1"
        ],
        "properties": {
          "rangeA1": {
            "type": "string",
            "description": "Range to apply top-N highlighting to, in A1 notation"
          },
          "n": {
            "type": "number",
            "description": "Number of top values to highlight (default 10)"
          },
          "percent": {
            "type": "boolean",
            "description": "If true, treat n as a percentage instead of absolute count"
          },
          "backgroundHex": {
            "type": "string",
            "description": "Background color hex for highlighted cells, e.g. #FFA500"
          }
        }
      },
      "examples_en": [
        "Highlight top 10 values in B2:B50",
        "Mark the top 5% in orange"
      ],
      "examples_pt": [
        "Destacar os 10 maiores valores em B2:B50",
        "Marcar os 5% maiores em laranja"
      ]
    },
    "XLSX_SORT_RANGE": {
      "runtimeOperator": "COMPUTE_BUNDLE",
      "preview_render_type": "structural_diff",
      "requires_confirmation": true,
      "undo_strategy": "restore_previous_range_order",
      "schema": {
        "type": "object",
        "required": [
          "rangeA1",
          "sortBy"
        ],
        "properties": {
          "rangeA1": {
            "type": "string"
          },
          "sortBy": {
            "type": "string"
          },
          "direction": {
            "type": "string"
          }
        }
      },
      "examples_en": [
        "Apply sort range to the selected range.",
        "Run sort range on SUMMARY 1!D35:D48.",
        "Please sort range in the current sheet selection.",
        "Do sort range only on the highlighted cells.",
        "Set up sort range without changing unrelated cells."
      ],
      "examples_pt": [
        "Aplique sort range no intervalo selecionado.",
        "Execute sort range em SUMMARY 1!D35:D48.",
        "Por favor, faça sort range na seleção da planilha atual.",
        "Faça sort range apenas nas células destacadas.",
        "Configure sort range sem alterar células não relacionadas."
      ]
    },
    "XLSX_FILTER_APPLY": {
      "runtimeOperator": "COMPUTE_BUNDLE",
      "preview_render_type": "structural_diff",
      "requires_confirmation": true,
      "undo_strategy": "restore_previous_filter_state",
      "schema": {
        "type": "object",
        "required": [
          "rangeA1"
        ],
        "properties": {
          "rangeA1": {
            "type": "string"
          },
          "filter": {
            "type": "object"
          }
        }
      },
      "examples_en": [
        "Apply filter apply to the selected range.",
        "Run filter apply on SUMMARY 1!D35:D48.",
        "Please filter apply in the current sheet selection.",
        "Do filter apply only on the highlighted cells.",
        "Set up filter apply without changing unrelated cells."
      ],
      "examples_pt": [
        "Aplique filter apply no intervalo selecionado.",
        "Execute filter apply em SUMMARY 1!D35:D48.",
        "Por favor, faça filter apply na seleção da planilha atual.",
        "Faça filter apply apenas nas células destacadas.",
        "Configure filter apply sem alterar células não relacionadas."
      ]
    },
    "XLSX_FILTER_CLEAR": {
      "runtimeOperator": "COMPUTE_BUNDLE",
      "preview_render_type": "structural_diff",
      "requires_confirmation": false,
      "undo_strategy": "restore_previous_filter_state",
      "schema": {
        "type": "object",
        "required": [
          "rangeA1"
        ],
        "properties": {
          "rangeA1": {
            "type": "string"
          }
        }
      },
      "examples_en": [
        "Apply filter clear to the selected range.",
        "Run filter clear on SUMMARY 1!D35:D48.",
        "Please filter clear in the current sheet selection.",
        "Do filter clear only on the highlighted cells.",
        "Set up filter clear without changing unrelated cells."
      ],
      "examples_pt": [
        "Aplique filter clear no intervalo selecionado.",
        "Execute filter clear em SUMMARY 1!D35:D48.",
        "Por favor, faça filter clear na seleção da planilha atual.",
        "Faça filter clear apenas nas células destacadas.",
        "Configure filter clear sem alterar células não relacionadas."
      ]
    },
    "XLSX_TABLE_CREATE": {
      "runtimeOperator": "COMPUTE_BUNDLE",
      "preview_render_type": "structural_diff",
      "requires_confirmation": true,
      "undo_strategy": "restore_previous_table_state",
      "schema": {
        "type": "object",
        "required": [
          "rangeA1"
        ],
        "properties": {
          "rangeA1": {
            "type": "string"
          },
          "hasHeaders": {
            "type": "boolean"
          }
        }
      },
      "examples_en": [
        "Apply table create to the selected range.",
        "Run table create on SUMMARY 1!D35:D48.",
        "Please table create in the current sheet selection.",
        "Do table create only on the highlighted cells.",
        "Set up table create without changing unrelated cells."
      ],
      "examples_pt": [
        "Aplique table create no intervalo selecionado.",
        "Execute table create em SUMMARY 1!D35:D48.",
        "Por favor, faça table create na seleção da planilha atual.",
        "Faça table create apenas nas células destacadas.",
        "Configure table create sem alterar células não relacionadas."
      ]
    },
    "XLSX_DATA_VALIDATION_SET": {
      "runtimeOperator": "COMPUTE_BUNDLE",
      "preview_render_type": "format_diff",
      "requires_confirmation": true,
      "undo_strategy": "restore_previous_validation_state",
      "schema": {
        "type": "object",
        "required": [
          "rangeA1",
          "validation"
        ],
        "properties": {
          "rangeA1": {
            "type": "string"
          },
          "validation": {
            "type": "object"
          }
        }
      },
      "examples_en": [
        "Apply data validation set to the selected range.",
        "Run data validation set on SUMMARY 1!D35:D48.",
        "Please data validation set in the current sheet selection.",
        "Do data validation set only on the highlighted cells.",
        "Set up data validation set without changing unrelated cells."
      ],
      "examples_pt": [
        "Aplique data validation set no intervalo selecionado.",
        "Execute data validation set em SUMMARY 1!D35:D48.",
        "Por favor, faça data validation set na seleção da planilha atual.",
        "Faça data validation set apenas nas células destacadas.",
        "Configure data validation set sem alterar células não relacionadas."
      ]
    },
    "XLSX_FREEZE_PANES": {
      "runtimeOperator": "COMPUTE_BUNDLE",
      "preview_render_type": "structural_diff",
      "requires_confirmation": false,
      "undo_strategy": "restore_previous_view_state",
      "schema": {
        "type": "object",
        "required": [
          "sheetName",
          "row",
          "column"
        ],
        "properties": {
          "sheetName": {
            "type": "string"
          },
          "row": {
            "type": "number"
          },
          "column": {
            "type": "number"
          }
        }
      },
      "examples_en": [
        "Apply freeze panes to the selected range.",
        "Run freeze panes on SUMMARY 1!D35:D48.",
        "Please freeze panes in the current sheet selection.",
        "Do freeze panes only on the highlighted cells.",
        "Set up freeze panes without changing unrelated cells."
      ],
      "examples_pt": [
        "Aplique freeze panes no intervalo selecionado.",
        "Execute freeze panes em SUMMARY 1!D35:D48.",
        "Por favor, faça freeze panes na seleção da planilha atual.",
        "Faça freeze panes apenas nas células destacadas.",
        "Configure freeze panes sem alterar células não relacionadas."
      ]
    },
    "XLSX_HIDE_ROWS_COLS": {
      "runtimeOperator": "EDIT_RANGE",
      "preview_render_type": "structural_diff",
      "requires_confirmation": true,
      "undo_strategy": "snapshot",
      "schema": {
        "type": "object",
        "properties": {
          "rows": {
            "type": "array",
            "items": {
              "type": "number"
            },
            "description": "1-based row numbers to hide"
          },
          "columns": {
            "type": "array",
            "items": {
              "type": "number"
            },
            "description": "1-based column numbers to hide"
          }
        }
      },
      "examples_en": [
        "Hide rows 5 through 10",
        "Hide columns C and D"
      ],
      "examples_pt": [
        "Ocultar linhas 5 a 10",
        "Ocultar colunas C e D"
      ]
    },
    "XLSX_SHOW_ROWS_COLS": {
      "runtimeOperator": "EDIT_RANGE",
      "preview_render_type": "structural_diff",
      "requires_confirmation": false,
      "undo_strategy": "snapshot",
      "schema": {
        "type": "object",
        "properties": {
          "rows": {
            "type": "array",
            "items": {
              "type": "number"
            },
            "description": "1-based row numbers to unhide"
          },
          "columns": {
            "type": "array",
            "items": {
              "type": "number"
            },
            "description": "1-based column numbers to unhide"
          }
        }
      },
      "examples_en": [
        "Show hidden rows 5 to 10",
        "Unhide columns C and D"
      ],
      "examples_pt": [
        "Mostrar linhas ocultas 5 a 10",
        "Reexibir colunas C e D"
      ]
    },
    "XLSX_CHART_CREATE": {
      "runtimeOperator": "CREATE_CHART",
      "preview_render_type": "chart_diff",
      "requires_confirmation": true,
      "undo_strategy": "snapshot",
      "schema": {
        "type": "object",
        "required": [
          "rangeA1"
        ],
        "properties": {
          "rangeA1": {
            "type": "string",
            "description": "Data range for the chart, in A1 notation"
          },
          "type": {
            "type": "string",
            "description": "Chart type, e.g. bar, line, pie, scatter, area"
          },
          "title": {
            "type": "string",
            "description": "Chart title"
          }
        }
      },
      "examples_en": [
        "Create a bar chart from A1:C10",
        "Make a pie chart of the sales data"
      ],
      "examples_pt": [
        "Criar gráfico de barras de A1:C10",
        "Fazer gráfico de pizza dos dados de vendas"
      ]
    },
    "XLSX_CHART_SET_SERIES": {
      "runtimeOperator": "CREATE_CHART",
      "preview_render_type": "chart_diff",
      "requires_confirmation": false,
      "undo_strategy": "snapshot",
      "schema": {
        "type": "object",
        "required": [
          "rangeA1"
        ],
        "properties": {
          "rangeA1": {
            "type": "string",
            "description": "Data range for the chart series, in A1 notation"
          },
          "chartType": {
            "type": "string",
            "description": "Chart type to apply to the series"
          },
          "seriesRange": {
            "type": "string",
            "description": "Specific range for the series data"
          }
        }
      },
      "examples_en": [
        "Update chart series to include column D",
        "Change chart data range to A1:D20"
      ],
      "examples_pt": [
        "Atualizar séries do gráfico para incluir coluna D",
        "Mudar intervalo de dados do gráfico para A1:D20"
      ]
    },
    "XLSX_CHART_SET_TITLES": {
      "runtimeOperator": "CREATE_CHART",
      "preview_render_type": "chart_diff",
      "requires_confirmation": false,
      "undo_strategy": "snapshot",
      "schema": {
        "type": "object",
        "required": [
          "rangeA1"
        ],
        "properties": {
          "rangeA1": {
            "type": "string",
            "description": "Chart anchor range for identification"
          },
          "title": {
            "type": "string",
            "description": "Main chart title"
          },
          "xAxisTitle": {
            "type": "string",
            "description": "X-axis title label"
          },
          "yAxisTitle": {
            "type": "string",
            "description": "Y-axis title label"
          }
        }
      },
      "examples_en": [
        "Set chart title to 'Revenue by Month'",
        "Add axis labels to the chart"
      ],
      "examples_pt": [
        "Definir título do gráfico como 'Receita por Mês'",
        "Adicionar rótulos de eixo ao gráfico"
      ]
    },
    "XLSX_CHART_SET_AXES": {
      "runtimeOperator": "CREATE_CHART",
      "preview_render_type": "chart_diff",
      "requires_confirmation": false,
      "undo_strategy": "snapshot",
      "schema": {
        "type": "object",
        "required": [
          "rangeA1"
        ],
        "properties": {
          "rangeA1": {
            "type": "string",
            "description": "Chart anchor range for identification"
          },
          "xAxisMin": {
            "type": "number",
            "description": "Minimum value for the X axis"
          },
          "xAxisMax": {
            "type": "number",
            "description": "Maximum value for the X axis"
          },
          "yAxisMin": {
            "type": "number",
            "description": "Minimum value for the Y axis"
          },
          "yAxisMax": {
            "type": "number",
            "description": "Maximum value for the Y axis"
          }
        }
      },
      "examples_en": [
        "Set Y-axis range from 0 to 1000",
        "Configure chart axes"
      ],
      "examples_pt": [
        "Definir eixo Y de 0 a 1000",
        "Configurar eixos do gráfico"
      ]
    },
    "XLSX_CHART_MOVE_RESIZE": {
      "runtimeOperator": "CREATE_CHART",
      "preview_render_type": "chart_diff",
      "requires_confirmation": true,
      "undo_strategy": "restore_previous_chart_anchor",
      "schema": {
        "type": "object",
        "required": [
          "chartId"
        ],
        "properties": {
          "chartId": {
            "type": "number"
          },
          "anchor": {
            "type": "object"
          }
        }
      },
      "examples_en": [
        "Apply chart move resize to the selected range.",
        "Run chart move resize on SUMMARY 1!D35:D48.",
        "Please chart move resize in the current sheet selection.",
        "Do chart move resize only on the highlighted cells.",
        "Set up chart move resize without changing unrelated cells."
      ],
      "examples_pt": [
        "Aplique chart move resize no intervalo selecionado.",
        "Execute chart move resize em SUMMARY 1!D35:D48.",
        "Por favor, faça chart move resize na seleção da planilha atual.",
        "Faça chart move resize apenas nas células destacadas.",
        "Configure chart move resize sem alterar células não relacionadas."
      ]
    },
    "XLSX_CHART_DELETE": {
      "runtimeOperator": "CREATE_CHART",
      "preview_render_type": "chart_diff",
      "requires_confirmation": true,
      "undo_strategy": "snapshot",
      "schema": {
        "type": "object",
        "properties": {
          "chartId": {
            "type": "string",
            "description": "Identifier of the chart to delete"
          },
          "rangeA1": {
            "type": "string",
            "description": "Chart anchor range for identification if chartId is unknown"
          }
        }
      },
      "examples_en": [
        "Delete the chart",
        "Remove the bar chart"
      ],
      "examples_pt": [
        "Excluir o gráfico",
        "Remover o gráfico de barras"
      ]
    },
    "XLSX_REMOVE_DUPLICATES": {
      "runtimeOperator": "COMPUTE",
      "preview_render_type": "range_diff",
      "requires_confirmation": true,
      "undo_strategy": "snapshot",
      "schema": {
        "type": "object",
        "required": [
          "rangeA1"
        ],
        "properties": {
          "rangeA1": {
            "type": "string",
            "description": "A1 range containing data to deduplicate"
          },
          "keyColumns": {
            "type": "array",
            "items": {
              "type": "number"
            },
            "description": "1-based column indices to use as dedup key (omit for all columns)"
          },
          "hasHeader": {
            "type": "boolean",
            "description": "Whether the first row is a header (default true)"
          }
        }
      },
      "examples_en": [
        "Remove duplicates from this range",
        "Deduplicate rows based on column A"
      ],
      "examples_pt": [
        "Remover duplicatas deste intervalo",
        "Deduplicar linhas com base na coluna A"
      ]
    },
    "XLSX_TRIM_WHITESPACE": {
      "runtimeOperator": "COMPUTE",
      "preview_render_type": "range_diff",
      "requires_confirmation": false,
      "undo_strategy": "snapshot",
      "schema": {
        "type": "object",
        "required": [
          "rangeA1"
        ],
        "properties": {
          "rangeA1": {
            "type": "string",
            "description": "A1 range of cells to trim whitespace from"
          }
        }
      },
      "examples_en": [
        "Trim whitespace from these cells",
        "Clean up extra spaces"
      ],
      "examples_pt": [
        "Remover espaços em branco destas células",
        "Limpar espaços extras"
      ]
    },
    "XLSX_NORMALIZE_VALUES": {
      "runtimeOperator": "COMPUTE",
      "preview_render_type": "range_diff",
      "requires_confirmation": false,
      "undo_strategy": "snapshot",
      "schema": {
        "type": "object",
        "required": [
          "rangeA1",
          "normalization"
        ],
        "properties": {
          "rangeA1": {
            "type": "string",
            "description": "A1 range of cells to normalize"
          },
          "normalization": {
            "type": "string",
            "enum": [
              "dates",
              "numbers",
              "text_case"
            ],
            "description": "Type of normalization to apply"
          },
          "textCase": {
            "type": "string",
            "enum": [
              "upper",
              "lower",
              "title"
            ],
            "description": "Target text case (only for text_case normalization)"
          },
          "dateFormat": {
            "type": "string",
            "description": "Target date format (only for dates normalization)"
          }
        }
      },
      "examples_en": [
        "Normalize dates to ISO format",
        "Standardize text to uppercase",
        "Convert formatted numbers to plain numbers"
      ],
      "examples_pt": [
        "Normalizar datas para formato ISO",
        "Padronizar texto em maiúsculas",
        "Converter números formatados para números simples"
      ]
    },
    "XLSX_SET_PROTECTION": {
      "runtimeOperator": "COMPUTE",
      "preview_render_type": "sheet_info",
      "requires_confirmation": true,
      "undo_strategy": "snapshot",
      "schema": {
        "type": "object",
        "required": [
          "sheetName"
        ],
        "properties": {
          "sheetName": {
            "type": "string",
            "description": "Name of the sheet to protect"
          },
          "password": {
            "type": "string",
            "description": "Optional password for sheet protection"
          }
        }
      },
      "examples_en": [
        "Protect this sheet",
        "Lock the sheet with a password"
      ],
      "examples_pt": [
        "Proteger esta planilha",
        "Bloquear a planilha com senha"
      ]
    },
    "XLSX_LOCK_CELLS": {
      "runtimeOperator": "COMPUTE",
      "preview_render_type": "range_diff",
      "requires_confirmation": false,
      "undo_strategy": "snapshot",
      "schema": {
        "type": "object",
        "required": [
          "rangeA1",
          "locked"
        ],
        "properties": {
          "rangeA1": {
            "type": "string",
            "description": "A1 range of cells to lock or unlock"
          },
          "locked": {
            "type": "boolean",
            "description": "Whether to lock (true) or unlock (false) cells"
          },
          "hidden": {
            "type": "boolean",
            "description": "Whether to hide cell formulas (default false)"
          }
        }
      },
      "examples_en": [
        "Lock cells A1:D10",
        "Unlock the header row"
      ],
      "examples_pt": [
        "Bloquear células A1:D10",
        "Desbloquear a linha de cabeçalho"
      ]
    }
  }
}
